sigmasms.py
sigmasms-1.2.1.dist-info/METADATA
sigmasms-1.2.1.dist-info/WHEEL
sigmasms-1.2.1.dist-info/top_level.txt
sigmasms-1.2.1.dist-info/RECORD
