Metadata-Version: 2.2
Name: sigmasms
Version: 1.2.1
Summary: Tool for easy working with SigmaSMS API
Home-page: https://github.com/mrslow/sigmasms
Author: Anton Shchetikhin
Author-email: animal2k@gmail.com
Keywords: api sigmasms client
Requires-Python: >=3.10
Requires-Dist: httpx
Dynamic: author
Dynamic: author-email
Dynamic: description
Dynamic: description-content-type
Dynamic: home-page
Dynamic: keywords
Dynamic: requires-dist
Dynamic: requires-python
Dynamic: summary
